{
    "data": [
        {
            "server": "http://iptv.journalsat.com",
            "port": 25461,
            "username": "726152140",
            "password": "journalsat"
        },
       {
            "server": "http://iptv.journalsat.com",
            "port": 25461,
            "username": "894275377",
            "password": "journalsat"
        },
        {
            "server": "http://th4.online",
            "port": 2095,
            "username": "RESTREAM65MIO",
            "password": "5747379"
        },
        {
            "server": "138.255.102.3",
            "port": 25461,
            "username": "FOXSPORTS1HDsd",
            "password": "RRZKamZw9a"
        },
        {
            "server": "http://da1981.xyz",
            "port": 80,
            "username": "Muhammed-Loay",
            "password": "hgkj89gggGHHGJUZghhhj"
        },
        {
            "server": "http://hd-max.org",
            "port": 8080 ,
            "username": "SFjLSkJ1qk",
            "password": "zbocNLmJvW"
        },
        {
            "server": "http://195.62.32.123",
            "port": 2095,
            "username": "mimi",
            "password": "Ab123456"
        },
        {
            "server": "http://iptv.journalsat.com",
            "port": 25461,
            "username": "360917929",
            "password": "journalsat"
        }
    ]
}